setup.py
vymgmt/__init__.py
vymgmt/router.py
vymgmt.egg-info/PKG-INFO
vymgmt.egg-info/SOURCES.txt
vymgmt.egg-info/dependency_links.txt
vymgmt.egg-info/requires.txt
vymgmt.egg-info/top_level.txt